README.rst
setup.cfg
setup.py
Multiple_Rotor_Enigma/Multiple_Rotor_Enigma.py
Multiple_Rotor_Enigma/__init__.py
Multiple_Rotor_Enigma.egg-info/PKG-INFO
Multiple_Rotor_Enigma.egg-info/SOURCES.txt
Multiple_Rotor_Enigma.egg-info/dependency_links.txt
Multiple_Rotor_Enigma.egg-info/top_level.txt