Metadata-Version: 2.1
Name: Multiple-Rotor-Enigma
Version: 0.2.1
Summary: An enhanced simulation of the enigma machine
Author: Aradhya Goel
Author-email: aradhyagnov@gmail.com
License: MIT
Keywords: Enigma
Classifier: Development Status :: 3 - Alpha
Classifier: Intended Audience :: Developers
